[
  {
    "ContainingType": "CafeEmployeeManagement.Controllers.CafeController",
    "Method": "GetCafes",
    "RelativePath": "api/Cafe",
    "HttpMethod": "GET",
    "IsController": true,
    "Order": 0,
    "Parameters": [
      {
        "Name": "location",
        "Type": "System.String",
        "IsRequired": false
      }
    ],
    "ReturnTypes": [
      {
        "Type": "System.Collections.Generic.IEnumerable\u00601[[CafeEmployeeManagement.Models.Cafe, CafeEmployeeManagement, Version=1.0.0.0, Culture=neutral, PublicKeyToken=null]]",
        "MediaTypes": [
          "text/plain",
          "application/json",
          "text/json"
        ],
        "StatusCode": 200
      }
    ]
  },
  {
    "ContainingType": "CafeEmployeeManagement.Controllers.CafeController",
    "Method": "PostCafe",
    "RelativePath": "api/Cafe",
    "HttpMethod": "POST",
    "IsController": true,
    "Order": 0,
    "Parameters": [
      {
        "Name": "cafe",
        "Type": "CafeEmployeeManagement.Models.Cafe",
        "IsRequired": true
      }
    ],
    "ReturnTypes": [
      {
        "Type": "CafeEmployeeManagement.Models.Cafe",
        "MediaTypes": [
          "text/plain",
          "application/json",
          "text/json"
        ],
        "StatusCode": 200
      }
    ]
  },
  {
    "ContainingType": "CafeEmployeeManagement.Controllers.CafeController",
    "Method": "PutCafe",
    "RelativePath": "api/Cafe/{id}",
    "HttpMethod": "PUT",
    "IsController": true,
    "Order": 0,
    "Parameters": [
      {
        "Name": "id",
        "Type": "System.Guid",
        "IsRequired": true
      },
      {
        "Name": "cafe",
        "Type": "CafeEmployeeManagement.Models.Cafe",
        "IsRequired": true
      }
    ],
    "ReturnTypes": []
  },
  {
    "ContainingType": "CafeEmployeeManagement.Controllers.CafeController",
    "Method": "DeleteCafe",
    "RelativePath": "api/Cafe/{id}",
    "HttpMethod": "DELETE",
    "IsController": true,
    "Order": 0,
    "Parameters": [
      {
        "Name": "id",
        "Type": "System.Guid",
        "IsRequired": true
      }
    ],
    "ReturnTypes": []
  },
  {
    "ContainingType": "CafeEmployeeManagement.Controllers.EmployeesController",
    "Method": "GetEmployees",
    "RelativePath": "api/Employees",
    "HttpMethod": "GET",
    "IsController": true,
    "Order": 0,
    "Parameters": [],
    "ReturnTypes": [
      {
        "Type": "System.Collections.Generic.IEnumerable\u00601[[CafeEmployeeManagement.Models.Employee, CafeEmployeeManagement, Version=1.0.0.0, Culture=neutral, PublicKeyToken=null]]",
        "MediaTypes": [
          "text/plain",
          "application/json",
          "text/json"
        ],
        "StatusCode": 200
      }
    ]
  },
  {
    "ContainingType": "CafeEmployeeManagement.Controllers.EmployeesController",
    "Method": "PostEmployee",
    "RelativePath": "api/Employees",
    "HttpMethod": "POST",
    "IsController": true,
    "Order": 0,
    "Parameters": [
      {
        "Name": "employee",
        "Type": "CafeEmployeeManagement.Models.Employee",
        "IsRequired": true
      }
    ],
    "ReturnTypes": [
      {
        "Type": "CafeEmployeeManagement.Models.Employee",
        "MediaTypes": [
          "text/plain",
          "application/json",
          "text/json"
        ],
        "StatusCode": 200
      }
    ]
  },
  {
    "ContainingType": "CafeEmployeeManagement.Controllers.EmployeesController",
    "Method": "GetEmployee",
    "RelativePath": "api/Employees/{id}",
    "HttpMethod": "GET",
    "IsController": true,
    "Order": 0,
    "Parameters": [
      {
        "Name": "id",
        "Type": "System.String",
        "IsRequired": true
      }
    ],
    "ReturnTypes": [
      {
        "Type": "CafeEmployeeManagement.Models.Employee",
        "MediaTypes": [
          "text/plain",
          "application/json",
          "text/json"
        ],
        "StatusCode": 200
      }
    ]
  },
  {
    "ContainingType": "CafeEmployeeManagement.Controllers.EmployeesController",
    "Method": "PutEmployee",
    "RelativePath": "api/Employees/{id}",
    "HttpMethod": "PUT",
    "IsController": true,
    "Order": 0,
    "Parameters": [
      {
        "Name": "id",
        "Type": "System.String",
        "IsRequired": true
      },
      {
        "Name": "employee",
        "Type": "CafeEmployeeManagement.Models.Employee",
        "IsRequired": true
      }
    ],
    "ReturnTypes": []
  },
  {
    "ContainingType": "CafeEmployeeManagement.Controllers.EmployeesController",
    "Method": "DeleteEmployee",
    "RelativePath": "api/Employees/{id}",
    "HttpMethod": "DELETE",
    "IsController": true,
    "Order": 0,
    "Parameters": [
      {
        "Name": "id",
        "Type": "System.String",
        "IsRequired": true
      }
    ],
    "ReturnTypes": []
  },
  {
    "ContainingType": "CafeEmployeeManagement.Controllers.WeatherForecastController",
    "Method": "Get",
    "RelativePath": "WeatherForecast",
    "HttpMethod": "GET",
    "IsController": true,
    "Order": 0,
    "Parameters": [],
    "ReturnTypes": [
      {
        "Type": "System.Collections.Generic.IEnumerable\u00601[[CafeEmployeeManagement.WeatherForecast, CafeEmployeeManagement, Version=1.0.0.0, Culture=neutral, PublicKeyToken=null]]",
        "MediaTypes": [
          "text/plain",
          "application/json",
          "text/json"
        ],
        "StatusCode": 200
      }
    ],
    "EndpointName": "GetWeatherForecast"
  }
]